LICENSE.txt
MANIFEST.in
README.md
pypinex_info.json
setup.py
documentation/general.xmd
documentation/introduction.xmd
documentation/commands/00_overview.xmd
documentation/commands/01_commands.xmd
examples/demo_bz2.py
examples/demo_gz.py
examples/demo_tar.py
examples/demo_uploadpack1.py
examples/demo_uploadpack2.py
examples/demo_xz.py
examples/foo_bar.txt
examples/hello_world.txt
examples/the_quick.txt
pypinex_pack/AddToUploadPack.py
pypinex_pack/CloseUploadPack.py
pypinex_pack/CompressUploadPack.py
pypinex_pack/CreateUploadPack.py
pypinex_pack/PackBZip2.py
pypinex_pack/PackGZip.py
pypinex_pack/PackXZ.py
pypinex_pack/Tar.py
pypinex_pack/UnpackBZip2.py
pypinex_pack/UnpackGZip.py
pypinex_pack/UnpackXZ.py
pypinex_pack/__init__.py
pypinex_pack.egg-info/PKG-INFO
pypinex_pack.egg-info/SOURCES.txt
pypinex_pack.egg-info/dependency_links.txt
pypinex_pack.egg-info/not-zip-safe
pypinex_pack.egg-info/requires.txt
pypinex_pack.egg-info/top_level.txt