Metadata-Version: 2.1
Name: pypinex-pack
Version: 0.2021.3.24
Summary: PyPine extension that supports various forms of compressing/uncompressing of files: gzip, bzip2, xz, tar and uploadpack.
Home-page: UNKNOWN
Author: Jürgen Knauth
Author-email: pubsrc@binary-overflow.de
License: Apache2
Keywords: pypine,pypinex,gzip,bzip2,xz,uploadpack,tar
Platform: UNKNOWN
Classifier: Development Status :: 4 - Beta
Classifier: License :: OSI Approved :: Apache Software License
Classifier: Programming Language :: Python :: 3
